pyfmt.py
pyfmt-0.1.data/scripts/pyfmt
pyfmt-0.1.dist-info/top_level.txt
pyfmt-0.1.dist-info/RECORD
pyfmt-0.1.dist-info/entry_points.txt
pyfmt-0.1.dist-info/WHEEL
pyfmt-0.1.dist-info/pydist.json
pyfmt-0.1.dist-info/DESCRIPTION.rst
pyfmt-0.1.dist-info/METADATA
