Metadata-Version: 2.0
Name: pyfmt
Version: 0.1
Summary: automatic code formatter for python following pep8 using baron FST, like gofmt
Home-page: https://github.com/Psycojoker/pyfmt
Author: Laurent Peuch
Author-email: cortex@worlddomination.be
License: gplv3+
Keywords: pep8 formatting baron fst code fmt gofmt
Platform: UNKNOWN
Classifier: Development Status :: 4 - Beta
Classifier: Environment :: Console
Classifier: Intended Audience :: Developers
Classifier: License :: OSI Approved :: GNU General Public License v3 or later (GPLv3+)
Classifier: Programming Language :: Python :: 2.7
Classifier: Topic :: Software Development :: Libraries
Classifier: Topic :: Software Development :: Quality Assurance
Classifier: Topic :: Utilities
Requires-Dist: baron (<=0.3,<0.4)
